{
  "video_id": "emostim_01_TheShining_clip_2",
  "segment_id": "s023",
  "time_range": [
    110.0,
    115.0
  ],
  "visual_description": "A woman with long, dark hair, wearing a blue bathrobe, stands with her back to the camera. She is looking out a frosted window. A small child in a red sweater is clinging to the woman's back, looking over her shoulder with a worried expression. The scene is set in a bathroom, indicated by the white tiled walls with a dark stripe. The window is covered in a thick layer of frost, obscuring the view outside. The camera is positioned at a medium distance, capturing the interaction between the two characters. The shot is static. The audio is filled with a tense and suspenseful orchestral score, creating a feeling of dread and anticipation. The music is driven by a low, pulsing string melody that builds steadily in volume and intensity. Layered over this are high-pitched, eerie notes that create a chilling and unsettling atmosphere, suggesting danger is approaching. There is no dialogue or narration, allowing the powerful, ominous music to dominate the soundscape.\n\nThe view shifts to a close-up of the frosted window from the outside. The window is framed by a thick, dark border, and the ground in front of it is completely covered in a deep layer of snow. The frosted glass is illuminated from within, creating a stark contrast with",
  "visual_objective": {
    "people": [],
    "scene": {
      "location": "",
      "setting": ""
    },
    "objects": [],
    "interactions": [],
    "key_actions": [],
    "visibility_notes": ""
  },
  "visual_expression": [],
  "audio_description": "",
  "temporal_description": "",
  "confidence": "medium",
  "evidence_strength": "ambiguous",
  "source_caption_model": "AVoCaDO-Captioner/AVoCaDO",
  "caption_status": "normalized",
  "raw_output_preview": "A woman with long, dark hair, wearing a blue bathrobe, stands with her back to the camera. She is looking out a frosted window. A small child in a red sweater is clinging to the woman's back, looking over her shoulder with a worried expression. The scene is set in a bathroom, indicated by the white tiled walls with a dark stripe. The window is covered in a thick layer of frost, obscuring the view outside. The camera is positioned at a medium distance, capturing the interaction between the two ch"
}