{
  "video_id": "moviechat_04_159",
  "segment_id": "s008",
  "time_range": [
    35.0,
    40.0
  ],
  "visual_objective": {
    "people": [
      {
        "person": "a man in a black suit and glasses",
        "visibility": "clearly visible",
        "position": "right",
        "action": "sitting at a table, looking down and then towards the other man"
      },
      {
        "person": "a man in a dark suit",
        "visibility": "clearly visible",
        "position": "left",
        "action": "sitting at a table, smoking a cigarette and looking at the other man"
      }
    ],
    "scene": {
      "location": "indoor room",
      "setting": "a dimly lit room with a dark table and a dark background"
    },
    "objects": [
      {
        "name": "table",
        "visibility": "clearly visible",
        "position": "center",
        "action": "supporting the men and objects"
      },
      {
        "name": "cigarette",
        "visibility": "clearly visible",
        "position": "left",
        "action": "being smoked"
      },
      {
        "name": "ashtray",
        "visibility": "clearly visible",
        "position": "left",
        "action": "on the table"
      }
    ],
    "interactions": [
      "The two men are seated opposite each other at a table, engaged in a tense conversation."
    ],
    "key_actions": [
      "The man on the left is smoking a cigarette.",
      "The man on the right is looking down and then towards the other man."
    ],
    "visibility_notes": ""
  },
  "visual_expression": [
    {
      "person": "a man in a black suit and glasses",
      "facial_cues": [
        "looking down",
        "looking towards the other man"
      ],
      "body_cues": [
        "sitting upright"
      ],
      "gaze": "looking down, then at the other man"
    },
    {
      "person": "a man in a dark suit",
      "facial_cues": [
        "smoking",
        "looking at the other man"
      ],
      "body_cues": [
        "sitting with arms on the table"
      ],
      "gaze": "at the other man"
    }
  ],
  "audio_description": "A male voice is speaking in a calm and serious tone.",
  "emotion_description": "The man on the left appears calm and serious, while the man on the right appears pensive and contemplative.",
  "confidence": "high",
  "evidence_strength": "clear"
}