{
  "video_id": "moviechat_03_160",
  "segment_id": "s056",
  "time_range": [
    275.0,
    280.0
  ],
  "visual_objective": {
    "people": [],
    "scene": {
      "location": "",
      "setting": ""
    },
    "objects": [],
    "interactions": [],
    "key_actions": [],
    "visibility_notes": ""
  },
  "visual_expression": [],
  "audio_description": "",
  "temporal_description": "(00:00-00:02) A man in a dark suit and tie, with headphones around his neck, speaks urgently into a small microphone. The scene is dark, with a blue digital overlay of scrolling numbers and text appearing, creating a sense of technological surveillance or data analysis. (Storyline: The scene opens with a sense of urgency and authority, as a character gives a command to initiate an arrest, setting a tense and action-oriented tone.) (Audio: 1) Tone of speech: Authoritative, urgent. 2) Background sounds or music: A low, tense, electronic hum begins to build.)\n(00:03-00:05) In a dimly lit, narrow hallway, two men in dark suits stand with their hands raised in surrender. One man holds a small, dark object, possibly a phone or a small weapon, up to his face. The scene is dark and chaotic, with a sense of immediate danger. (Storyline: This quick cut introduces two characters who are surrendering, suggesting they are the ones being arrested or are in a state of peril.) (Audio: 1) Tone of speech: N/A. 2) Background sounds or music: The tense, electronic music continues, punctuated by a sharp, percussive sound.)",
  "confidence": "medium",
  "evidence_strength": "ambiguous",
  "source_caption_model": "yaolily/TimeChat-Captioner-GRPO-7B",
  "caption_status": "normalized",
  "raw_output_preview": "(00:00-00:02) A man in a dark suit and tie, with headphones around his neck, speaks urgently into a small microphone. The scene is dark, with a blue digital overlay of scrolling numbers and text appearing, creating a sense of technological surveillance or data analysis. (Storyline: The scene opens with a sense of urgency and authority, as a character gives a command to initiate an arrest, setting a tense and action-oriented tone.) (Audio: 1) Tone of speech: Authoritative, urgent. 2) Background s"
}