{
  "video_id": "emostim_01_TheShining_clip_2",
  "segment_id": "s024",
  "time_range": [
    115.0,
    120.0
  ],
  "visual_objective": {
    "people": [],
    "scene": {
      "location": "",
      "setting": ""
    },
    "objects": [],
    "interactions": [],
    "key_actions": [],
    "visibility_notes": ""
  },
  "visual_expression": [],
  "audio_description": "",
  "temporal_description": "(00:00-00:01) A young girl with blonde hair, wearing a red and blue plaid pajama set, looks up with a terrified expression. Her eyes are wide with fear as she stares at something off-screen. The scene is dimly lit, with a warm light source casting a shadow behind her. (Storyline: This opening shot immediately establishes a tone of suspense and fear, introducing a character who is in a state of terror.) (Audio: 1) Tone of speech: N/A. 2) Background sounds or music: A low, ominous musical score begins to build tension.)\n(00:02-00:03) A man in a red robe violently swings a large, double-bladed axe, smashing it against a wooden door. The impact is forceful, sending splinters flying. (Storyline: This action escalates the tension, showing a character engaged in a violent struggle, likely trying to break into a room or escape.) (Audio: 1) Tone of speech: N/A. 2) Background sounds or music: The sound of the axe hitting the wood is loud and impactful, accompanied by the ongoing tense music.)\n(00:04-00:05) A woman in a purple robe is seen trapped and struggling to escape through a small, frosted glass window set into a wall of snow. She is pushing against the glass, her face showing desperation as she is buried in the white, cold ground. (Storyline: This scene introduces another character in peril, trapped and fighting for her life in a harsh, snowy environment, adding another layer of mystery to the events.) (Audio: 1) Tone of speech: N/A. 2) Background sounds or music: The tense, dramatic musical score continues.)\n(00:06-00:07) A woman in a dark, hooded cloak and a metal helmet stands in a dark, wet, and foggy alleyway. She stares forward with a menacing and determined expression, her face partially obscured by the shadows. (Storyline: This introduces a mysterious and threatening character, possibly an antagonist or a guard, adding to the film's dark and dangerous tone.) (Audio: 1) Tone of speech: N/A. 2) Background sounds or music: The suspenseful music continues, with a slight echo effect on the sound design to enhance the atmosphere.)",
  "confidence": "medium",
  "evidence_strength": "ambiguous",
  "source_caption_model": "yaolily/TimeChat-Captioner-GRPO-7B",
  "caption_status": "normalized",
  "raw_output_preview": "(00:00-00:01) A young girl with blonde hair, wearing a red and blue plaid pajama set, looks up with a terrified expression. Her eyes are wide with fear as she stares at something off-screen. The scene is dimly lit, with a warm light source casting a shadow behind her. (Storyline: This opening shot immediately establishes a tone of suspense and fear, introducing a character who is in a state of terror.) (Audio: 1) Tone of speech: N/A. 2) Background sounds or music: A low, ominous musical score be"
}