{
  "video_id": "moviechat_01_162",
  "segment_id": "s058",
  "time_range": [
    285.0,
    290.0
  ],
  "visual_objective": {
    "people": [],
    "scene": {
      "location": "",
      "setting": ""
    },
    "objects": [],
    "interactions": [],
    "key_actions": [],
    "visibility_notes": ""
  },
  "visual_expression": [],
  "audio_description": "",
  "temporal_description": "(00:00-00:08) The scene opens with a high-angle shot of a modern, multi-level office building. People in business attire are seen walking up and down the stairs and through the open-plan office spaces below. The lighting is dim and atmospheric, with fluorescent lights casting long shadows. The camera slowly zooms in on the central area. (Storyline: This establishing shot sets the scene, introducing the primary location of the investigation: a large, modern office building.) (Audio: 1) Tone of speech: The narrator's voice is calm and factual. 2) Background sounds or music: A low, tense, and suspenseful musical score begins to play, creating a sense of foreboding.)\n(00:09-00:13) The scene cuts to a close-up of a security monitor's face. He is a man in a light-colored shirt and tie, with a serious and focused expression. He stares intently at a screen displaying a CCTV feed of the office building's entrance. (Storyline: This introduces a key character, a security monitor, and establishes that the events are being watched on CCTV, adding a layer of surveillance to the narrative.) (Audio: 1) Tone of speech: The security monitor's tone is neutral and observational. 2) Background sounds or music: The tense, suspenseful music continues.)",
  "confidence": "medium",
  "evidence_strength": "ambiguous",
  "source_caption_model": "yaolily/TimeChat-Captioner-GRPO-7B",
  "caption_status": "normalized",
  "raw_output_preview": "(00:00-00:08) The scene opens with a high-angle shot of a modern, multi-level office building. People in business attire are seen walking up and down the stairs and through the open-plan office spaces below. The lighting is dim and atmospheric, with fluorescent lights casting long shadows. The camera slowly zooms in on the central area. (Storyline: This establishing shot sets the scene, introducing the primary location of the investigation: a large, modern office building.) (Audio: 1) Tone of sp"
}